LICENCE.txt
MANIFEST.in
README.rst
setup.py
cookie_law/__init__.py
cookie_law/models.py
cookie_law/locale/django.pot
cookie_law/locale/en/LC_MESSAGES/django.mo
cookie_law/locale/en/LC_MESSAGES/django.po
cookie_law/locale/fr/LC_MESSAGES/django.mo
cookie_law/locale/fr/LC_MESSAGES/django.po
cookie_law/static/js/cookie_law/cookie_law.js
cookie_law/templates/cookie_law/banner.html
cookie_law/templatetags/__init__.py
cookie_law/templatetags/cookie_law.py
emencia_cookie_law.egg-info/PKG-INFO
emencia_cookie_law.egg-info/SOURCES.txt
emencia_cookie_law.egg-info/dependency_links.txt
emencia_cookie_law.egg-info/not-zip-safe
emencia_cookie_law.egg-info/top_level.txt