Metadata-Version: 1.1
Name: emencia-cookie-law
Version: 0.2.1
Summary: 
